pyrandorg/__init__.py
pyrandorg-1.0.3.dist-info/LICENSE
pyrandorg-1.0.3.dist-info/METADATA
pyrandorg-1.0.3.dist-info/WHEEL
pyrandorg-1.0.3.dist-info/top_level.txt
pyrandorg-1.0.3.dist-info/RECORD
